ez_background_music.py
ez_background_music-1.0.0.dist-info/licenses/LICENSE
ez_background_music-1.0.0.dist-info/METADATA
ez_background_music-1.0.0.dist-info/WHEEL
ez_background_music-1.0.0.dist-info/top_level.txt
ez_background_music-1.0.0.dist-info/RECORD
