Metadata-Version: 2.4
Name: ez_background_music
Version: 1.0.0
Summary: A lightweight, cross-platform Python library for playing background music in CLI tools without blocking.
Home-page: https://github.com/yourusername/ez_background_music
Author: Your Name
Author-email: your.email@example.com
Keywords: background music cli audio non-blocking terminal
Classifier: Development Status :: 4 - Beta
Classifier: Intended Audience :: Developers
Classifier: Topic :: Multimedia :: Sound/Audio :: Players
Classifier: License :: OSI Approved :: MIT License
Classifier: Programming Language :: Python :: 3
Classifier: Operating System :: MacOS
Classifier: Operating System :: Microsoft :: Windows
Classifier: Operating System :: POSIX :: Linux
License-File: LICENSE
Dynamic: author
Dynamic: author-email
Dynamic: classifier
Dynamic: description
Dynamic: description-content-type
Dynamic: home-page
Dynamic: keywords
Dynamic: license-file
Dynamic: summary
